setup.py
geotwd/__init__.py
geotwd.egg-info/PKG-INFO
geotwd.egg-info/SOURCES.txt
geotwd.egg-info/dependency_links.txt
geotwd.egg-info/pbr.json
geotwd.egg-info/top_level.txt