Metadata-Version: 1.0
Name: geotwd
Version: 0.1
Summary: Conversion from x/y (TWD67 or TWD97) to lat/lon (WGS84)
Home-page: https://github.com/wagamama/geo-twd
Author: Yi-Lung (Bruce) Tsai
Author-email: wagamama.tsai@gmail.com
License: MIT
Keywords: twd67 twd97 wgs84 transform
Platform: UNKNOWN
